LICENSE
MANIFEST.in
README.rst
setup.py
./CHANGELOG.rst
./README.rst
./proclets/doc/changes.rst
./proclets/doc/channel.rst
./proclets/doc/example.rst
./proclets/doc/index.rst
./proclets/doc/intro.rst
./proclets/doc/proclet.rst
proclets/__init__.py
proclets/channel.py
proclets/mission.py
proclets/proclet.py
proclets/promise.py
proclets/tea.py
proclets/types.py
proclets.egg-info/PKG-INFO
proclets.egg-info/SOURCES.txt
proclets.egg-info/dependency_links.txt
proclets.egg-info/requires.txt
proclets.egg-info/top_level.txt
proclets.egg-info/zip-safe
proclets/doc/changes.rst
proclets/doc/channel.rst
proclets/doc/example.rst
proclets/doc/index.rst
proclets/doc/intro.rst
proclets/doc/proclet.rst
proclets/doc/html/changes.html
proclets/doc/html/channel.html
proclets/doc/html/example.html
proclets/doc/html/genindex.html
proclets/doc/html/index.html
proclets/doc/html/intro.html
proclets/doc/html/proclet.html
proclets/doc/html/search.html
proclets/doc/html/searchindex.js
proclets/doc/html/_sources/changes.rst.txt
proclets/doc/html/_sources/channel.rst.txt
proclets/doc/html/_sources/example.rst.txt
proclets/doc/html/_sources/index.rst.txt
proclets/doc/html/_sources/intro.rst.txt
proclets/doc/html/_sources/proclet.rst.txt
proclets/doc/html/_static/basic.css
proclets/doc/html/_static/doctools.js
proclets/doc/html/_static/documentation_options.js
proclets/doc/html/_static/file.png
proclets/doc/html/_static/jquery-3.5.1.js
proclets/doc/html/_static/jquery.js
proclets/doc/html/_static/language_data.js
proclets/doc/html/_static/minus.png
proclets/doc/html/_static/plus.png
proclets/doc/html/_static/pygments.css
proclets/doc/html/_static/searchtools.js
proclets/doc/html/_static/underscore-1.13.1.js
proclets/doc/html/_static/underscore.js
proclets/doc/html/_static/css/badge_only.css
proclets/doc/html/_static/css/theme.css
proclets/doc/html/_static/js/badge_only.js
proclets/doc/html/_static/js/html5shiv-printshiv.min.js
proclets/doc/html/_static/js/html5shiv.min.js
proclets/doc/html/_static/js/modernizr.min.js
proclets/doc/html/_static/js/theme.js
proclets/test/__init__.py
proclets/test/test_channel.py
proclets/test/test_mission.py
proclets/test/test_proclet.py
