Metadata-Version: 2.1
Name: proclets
Version: 0.18.0
Summary: A Lightweight Interacting Workflow library in Python.
Home-page: https://github.com/tundish/proclets
Author: D E Haynes
Author-email: tundish@gigeconomy.org.uk
License: UNKNOWN
Platform: UNKNOWN
Classifier: Operating System :: OS Independent
Classifier: Programming Language :: Python :: 3.8
Classifier: Programming Language :: Python :: 3.9
Classifier: License :: OSI Approved :: GNU General Public License v3 or later (GPLv3+)
Provides-Extra: dev
